{
  "moduleName": "laserminipod",
  "tables": [
    {
      "name": "handle",
      "dartName": "Handle",
      "module": "laserminipod",
      "schema": "public",
      "columns": [
        {
          "name": "id",
          "columnType": 6,
          "isNullable": false,
          "columnDefault": "nextval('handle_id_seq'::regclass)",
          "dartType": "int?"
        },
        {
          "name": "x",
          "columnType": 6,
          "isNullable": false,
          "dartType": "int"
        },
        {
          "name": "y",
          "columnType": 6,
          "isNullable": false,
          "dartType": "int"
        },
        {
          "name": "radius",
          "columnType": 6,
          "isNullable": false,
          "dartType": "int"
        }
      ],
      "foreignKeys": [],
      "indexes": [
        {
          "indexName": "handle_pkey",
          "elements": [
            {
              "type": 0,
              "definition": "id"
            }
          ],
          "type": "btree",
          "isUnique": true,
          "isPrimary": true
        }
      ],
      "managed": true
    },
    {
      "name": "spraywallroute",
      "dartName": "SpraywallRoute",
      "module": "laserminipod",
      "schema": "public",
      "columns": [
        {
          "name": "id",
          "columnType": 6,
          "isNullable": false,
          "columnDefault": "nextval('spraywallroute_id_seq'::regclass)",
          "dartType": "int?"
        },
        {
          "name": "name",
          "columnType": 0,
          "isNullable": false,
          "dartType": "String"
        },
        {
          "name": "description",
          "columnType": 0,
          "isNullable": true,
          "dartType": "String?"
        },
        {
          "name": "difficulty",
          "columnType": 6,
          "isNullable": false,
          "dartType": "int"
        },
        {
          "name": "handles",
          "columnType": 8,
          "isNullable": false,
          "dartType": "List<int>"
        },
        {
          "name": "creationDate",
          "columnType": 4,
          "isNullable": false,
          "columnDefault": "CURRENT_TIMESTAMP",
          "dartType": "DateTime"
        },
        {
          "name": "userInfoId",
          "columnType": 6,
          "isNullable": false,
          "dartType": "int"
        }
      ],
      "foreignKeys": [
        {
          "constraintName": "spraywallroute_fk_0",
          "columns": [
            "userInfoId"
          ],
          "referenceTable": "serverpod_user_info",
          "referenceTableSchema": "public",
          "referenceColumns": [
            "id"
          ],
          "onUpdate": 3,
          "onDelete": 3
        }
      ],
      "indexes": [
        {
          "indexName": "spraywallroute_pkey",
          "elements": [
            {
              "type": 0,
              "definition": "id"
            }
          ],
          "type": "btree",
          "isUnique": true,
          "isPrimary": true
        }
      ],
      "managed": true
    }
  ],
  "installedModules": [
    {
      "module": "serverpod",
      "version": "20240516151843329"
    },
    {
      "module": "serverpod_auth",
      "version": "20240520102713718"
    },
    {
      "module": "laserminipod",
      "version": "20250225215720574"
    }
  ],
  "migrationApiVersion": 1
}